pexnb.py
pexnb-0.1.1.dist-info/DESCRIPTION.rst
pexnb-0.1.1.dist-info/METADATA
pexnb-0.1.1.dist-info/RECORD
pexnb-0.1.1.dist-info/WHEEL
pexnb-0.1.1.dist-info/metadata.json
pexnb-0.1.1.dist-info/top_level.txt
