Metadata-Version: 2.0
Name: pexnb
Version: 0.1.1
Summary: Provide PEX-compatible entrypoint for Jupyter notebooks
Home-page: https://github.com/minrk/pexnb
Author: Min RK
Author-email: benjaminrk@gmail.com
License: MIT
Platform: UNKNOWN
Classifier: Intended Audience :: Developers
Classifier: License :: OSI Approved :: MIT License
Classifier: Programming Language :: Python
Classifier: Programming Language :: Python :: 2
Classifier: Programming Language :: Python :: 2.7
Classifier: Programming Language :: Python :: 3
Classifier: Programming Language :: Python :: 3.4
Requires-Dist: jupyter-client
Requires-Dist: notebook
